tethys_dataset_services/__init__.py
tethys_dataset_services/_version.py
tethys_dataset_services/utilities.py
tethys_dataset_services/valid_engines.py
tethys_dataset_services/base/__init__.py
tethys_dataset_services/base/dataset_engine_abc.py
tethys_dataset_services/base/spatial_dataset_engine_abc.py
tethys_dataset_services/engines/__init__.py
tethys_dataset_services/engines/ckan_engine.py
tethys_dataset_services/engines/geoserver_engine.py
tethys_dataset_services/engines/hydroshare_engine.py
tethys_dataset_services/resources/geoserver/xml_templates/coverage_template.xml
tethys_dataset_services/resources/geoserver/xml_templates/gwc_layer_template.xml
tethys_dataset_services/resources/geoserver/xml_templates/gwc_tile_cache_operation_template.xml
tethys_dataset_services/resources/geoserver/xml_templates/layer_group_template.xml
tethys_dataset_services/resources/geoserver/xml_templates/layer_template.xml
tethys_dataset_services/resources/geoserver/xml_templates/sql_view_template.xml
tethys_dataset_services-2.4.1.dist-info/licenses/LICENSE
tethys_dataset_services-2.4.1.dist-info/METADATA
tethys_dataset_services-2.4.1.dist-info/WHEEL
tethys_dataset_services-2.4.1.dist-info/top_level.txt
tethys_dataset_services-2.4.1.dist-info/RECORD
