Metadata-Version: 2.4
Name: tethys_dataset_services
Version: 2.4.1
Summary: A generic Python interface for dataset services such as GeoServer, CKAN, and HydroShare
Author-email: Nathan Swain <nswain@aquaveo.com>
License-Expression: BSD-2-Clause
Project-URL: Homepage, https://github.com/tethysplatform/tethys_dataset_services
Project-URL: Documentation, http://docs.tethysplatform.org/en/stable/tethys_sdk/tethys_services/spatial_dataset_service/base_reference.html
Classifier: Development Status :: 5 - Production/Stable
Classifier: Environment :: Web Environment
Classifier: Intended Audience :: Developers
Classifier: Natural Language :: English
Classifier: Operating System :: OS Independent
Classifier: Programming Language :: Python :: 3
Classifier: Programming Language :: Python :: 3.10
Classifier: Programming Language :: Python :: 3.11
Classifier: Programming Language :: Python :: 3.12
Classifier: Programming Language :: Python :: 3.13
Classifier: Programming Language :: Python :: Implementation
Classifier: Topic :: Scientific/Engineering
Classifier: Topic :: Scientific/Engineering :: GIS
Classifier: Topic :: Scientific/Engineering :: Information Analysis
Classifier: Topic :: Software Development :: Libraries
Classifier: Topic :: Utilities
Requires-Python: >=3.10
License-File: LICENSE
Requires-Dist: django
Requires-Dist: future
Requires-Dist: jinja2
Requires-Dist: owslib
Requires-Dist: geoserver-restconfig
Requires-Dist: requests
Requires-Dist: requests_toolbelt
Requires-Dist: sqlalchemy<2
Requires-Dist: psycopg2-binary
Provides-Extra: tests
Requires-Dist: tox; extra == "tests"
Dynamic: license-file
